metalattice/__init__.py
metalattice/_version.py
metalattice/logo.py
metalattice/abaqus/__init__.py
metalattice/geom/__init__.py
metalattice/lattice/__init__.py
metalattice/material/__init__.py
metalattice-0.3.15.dist-info/LICENSE
metalattice-0.3.15.dist-info/METADATA
metalattice-0.3.15.dist-info/WHEEL
metalattice-0.3.15.dist-info/top_level.txt
metalattice-0.3.15.dist-info/RECORD
