Metadata-Version: 2.1
Name: metalattice
Version: 0.3.15
Summary: A Python package to model lattice metamaterials, using Abaqus.
Author-email: Huang Lihao <huang-lihao@outlook.com>
Maintainer-email: Huang Lihao <huang-lihao@outlook.com>
License: MIT License
Keywords: lattice metamaterial,micropolar,cosserat,abaqus
Classifier: Development Status :: 3 - Alpha
Classifier: Programming Language :: Python :: 3
Classifier: Programming Language :: Fortran
Requires-Python: >=3.7
License-File: LICENSE
Requires-Dist: abaqus-mtx-parser
Requires-Dist: cython
Requires-Dist: f90nml
Requires-Dist: gfort2py
Requires-Dist: matplotlib
Requires-Dist: meshio
Requires-Dist: numpy
Requires-Dist: sympy
